bsb/__init__.py
bsb/bank_info.py
bsb/dataset.py
bsb/exceptions.py
bsb/models.py
bsb/parser.py
bsb/py.typed
bsb/static/bsb_directory.csv
bsb/static/bsb_prefix_rules.csv
bsb/static/npp_supported.csv
bsb/static/npp_unsupported.csv
bsb_lookup-0.0.6.dist-info/licenses/LICENSE
bsb_lookup-0.0.6.dist-info/WHEEL
bsb_lookup-0.0.6.dist-info/METADATA
bsb_lookup-0.0.6.dist-info/RECORD
