Metadata-Version: 2.4
Name: bsb-lookup
Version: 0.0.6
Summary: Lookup and enrich Australian BSBs
Author-email: Ilan Kessler <ilan@refundid.com>
Requires-Python: >=3.8.1
Classifier: Development Status :: 3 - Alpha
Classifier: Intended Audience :: Developers
Classifier: License :: OSI Approved :: MIT License
Classifier: Programming Language :: Python :: 3 :: Only
Classifier: Programming Language :: Python :: 3.8
Classifier: Programming Language :: Python :: 3.9
Classifier: Programming Language :: Python :: 3.10
Classifier: Programming Language :: Python :: 3.11
License-File: LICENSE
Requires-Dist: check-manifest==0.50 ; extra == "test"
Requires-Dist: ruff==0.9.0 ; extra == "test"
Requires-Dist: mypy==1.17.1 ; extra == "test"
Requires-Dist: pre-commit==4.0.1 ; extra == "test"
Requires-Dist: pytest==8.3.4 ; extra == "test"
Project-URL: Documentation, https://github.com/ilankessler/bsb-lookup#readme
Project-URL: Source, https://github.com/ilankessler/bsb-lookup
Project-URL: Tracker, https://github.com/ilankessler/bsb-lookup/issues
Provides-Extra: test
